[
{  "Line" : "Orange", "Trip" : 8365, "PlatformKey" : "OGREN", "InformationType" : "Predicted", "Time" : "3/21/2014 11:20:50 AM", "TimeRemaining" : "00:11:23", "Revenue" : "Revenue", "Route" : "0" },
{  "Line" : "Orange", "Trip" : 8365, "PlatformKey" : "OSTON", "InformationType" : "Predicted", "Time" : "3/21/2014 11:22:27 AM", "TimeRemaining" : "00:13:00", "Revenue" : "Revenue", "Route" : "0" },
{  "Line" : "Orange", "Trip" : 8365, "PlatformKey" : "OJACN", "InformationType" : "Predicted", "Time" : "3/21/2014 11:24:16 AM", "TimeRemaining" : "00:14:49", "Revenue" : "Revenue", "Route" : "0" },
{  "Line" : "Orange", "Trip" : 8365, "PlatformKey" : "OROXN", "InformationType" : "Predicted", "Time" : "3/21/2014 11:26:00 AM", "TimeRemaining" : "00:16:33", "Revenue" : "Revenue", "Route" : "0" },
{  "Line" : "Orange", "Trip" : 8365, "PlatformKey" : "ORUGN", "InformationType" : "Predicted", "Time" : "3/21/2014 11:27:30 AM", "TimeRemaining" : "00:18:03", "Revenue" : "Revenue", "Route" : "0" },
{  "Line" : "Orange", "Trip" : 8365, "PlatformKey" : "OMASN", "InformationType" : "Predicted", "Time" : "3/21/2014 11:29:01 AM", "TimeRemaining" : "00:19:34", "Revenue" : "Revenue", "Route" : "0" },
{  "Line" : "Orange", "Trip" : 482, "PlatformKey" : "OGREN", "InformationType" : "Predicted", "Time" : "3/21/2014 11:28:45 AM", "TimeRemaining" : "00:19:18", "Revenue" : "Revenue", "Route" : "0" },
{  "Line" : "Orange", "Trip" : 8754, "PlatformKey" : "OMALS", "InformationType" : "Predicted", "Time" : "3/21/2014 11:24:07 AM", "TimeRemaining" : "00:14:40", "Revenue" : "Revenue", "Route" : "0" },
{  "Line" : "Orange", "Trip" : 8754, "PlatformKey" : "OWELS", "InformationType" : "Predicted", "Time" : "3/21/2014 11:27:46 AM", "TimeRemaining" : "00:18:19", "Revenue" : "Revenue", "Route" : "0" },
{  "Line" : "Orange", "Trip" : 8755, "PlatformKey" : "OSULN", "InformationType" : "Predicted", "Time" : "3/21/2014 11:09:33 AM", "TimeRemaining" : "00:00:06", "Revenue" : "Revenue", "Route" : "0" },
{  "Line" : "Orange", "Trip" : 8755, "PlatformKey" : "OWELN", "InformationType" : "Predicted", "Time" : "3/21/2014 11:13:14 AM", "TimeRemaining" : "00:03:47", "Revenue" : "Revenue", "Route" : "0" },
{  "Line" : "Orange", "Trip" : 8755, "PlatformKey" : "OMALN", "InformationType" : "Predicted", "Time" : "3/21/2014 11:16:48 AM", "TimeRemaining" : "00:07:21", "Revenue" : "Revenue", "Route" : "0" },
{  "Line" : "Orange", "Trip" : 8755, "PlatformKey" : "OOAKN", "InformationType" : "Predicted", "Time" : "3/21/2014 11:19:06 AM", "TimeRemaining" : "00:09:39", "Revenue" : "Revenue", "Route" : "0" },
{  "Line" : "Orange", "Trip" : 8364, "PlatformKey" : "OJACS", "InformationType" : "Predicted", "Time" : "3/21/2014 11:10:22 AM", "TimeRemaining" : "00:00:55", "Revenue" : "Revenue", "Route" : "0" },
{  "Line" : "Orange", "Trip" : 8364, "PlatformKey" : "OSTOS", "InformationType" : "Predicted", "Time" : "3/21/2014 11:12:26 AM", "TimeRemaining" : "00:02:59", "Revenue" : "Revenue", "Route" : "0" },
{  "Line" : "Orange", "Trip" : 8364, "PlatformKey" : "OGRES", "InformationType" : "Predicted", "Time" : "3/21/2014 11:13:56 AM", "TimeRemaining" : "00:04:29", "Revenue" : "Revenue", "Route" : "0" },
{  "Line" : "Orange", "Trip" : 8364, "PlatformKey" : "OFORS", "InformationType" : "Predicted", "Time" : "3/21/2014 11:16:33 AM", "TimeRemaining" : "00:07:06", "Revenue" : "Revenue", "Route" : "0" },
{  "Line" : "Orange", "Trip" : 1156, "PlatformKey" : "OHAYN", "InformationType" : "Predicted", "Time" : "3/21/2014 11:10:09 AM", "TimeRemaining" : "00:00:42", "Revenue" : "Revenue", "Route" : "0" },
{  "Line" : "Orange", "Trip" : 1156, "PlatformKey" : "ONSTN", "InformationType" : "Predicted", "Time" : "3/21/2014 11:13:25 AM", "TimeRemaining" : "00:03:58", "Revenue" : "Revenue", "Route" : "0" },
{  "Line" : "Orange", "Trip" : 1156, "PlatformKey" : "OCOMN", "InformationType" : "Predicted", "Time" : "3/21/2014 11:15:34 AM", "TimeRemaining" : "00:06:07", "Revenue" : "Revenue", "Route" : "0" },
{  "Line" : "Orange", "Trip" : 1156, "PlatformKey" : "OSULN", "InformationType" : "Predicted", "Time" : "3/21/2014 11:17:38 AM", "TimeRemaining" : "00:08:11", "Revenue" : "Revenue", "Route" : "0" },
{  "Line" : "Orange", "Trip" : 1156, "PlatformKey" : "OWELN", "InformationType" : "Predicted", "Time" : "3/21/2014 11:21:19 AM", "TimeRemaining" : "00:11:52", "Revenue" : "Revenue", "Route" : "0" },
{  "Line" : "Orange", "Trip" : 1156, "PlatformKey" : "OMALN", "InformationType" : "Predicted", "Time" : "3/21/2014 11:24:53 AM", "TimeRemaining" : "00:15:26", "Revenue" : "Revenue", "Route" : "0" },
{  "Line" : "Orange", "Trip" : 1156, "PlatformKey" : "OOAKN", "InformationType" : "Predicted", "Time" : "3/21/2014 11:27:11 AM", "TimeRemaining" : "00:17:44", "Revenue" : "Revenue", "Route" : "0" },
{  "Line" : "Orange", "Trip" : 483, "PlatformKey" : "OBACS", "InformationType" : "Predicted", "Time" : "3/21/2014 11:10:55 AM", "TimeRemaining" : "00:01:28", "Revenue" : "Revenue", "Route" : "0" },
{  "Line" : "Orange", "Trip" : 483, "PlatformKey" : "OMASS", "InformationType" : "Predicted", "Time" : "3/21/2014 11:13:28 AM", "TimeRemaining" : "00:04:01", "Revenue" : "Revenue", "Route" : "0" },
{  "Line" : "Orange", "Trip" : 483, "PlatformKey" : "ORUGS", "InformationType" : "Predicted", "Time" : "3/21/2014 11:14:56 AM", "TimeRemaining" : "00:05:29", "Revenue" : "Revenue", "Route" : "0" },
{  "Line" : "Orange", "Trip" : 483, "PlatformKey" : "OROXS", "InformationType" : "Predicted", "Time" : "3/21/2014 11:16:39 AM", "TimeRemaining" : "00:07:12", "Revenue" : "Revenue", "Route" : "0" },
{  "Line" : "Orange", "Trip" : 483, "PlatformKey" : "OJACS", "InformationType" : "Predicted", "Time" : "3/21/2014 11:18:17 AM", "TimeRemaining" : "00:08:50", "Revenue" : "Revenue", "Route" : "0" },
{  "Line" : "Orange", "Trip" : 483, "PlatformKey" : "OSTOS", "InformationType" : "Predicted", "Time" : "3/21/2014 11:20:21 AM", "TimeRemaining" : "00:10:54", "Revenue" : "Revenue", "Route" : "0" },
{  "Line" : "Orange", "Trip" : 483, "PlatformKey" : "OGRES", "InformationType" : "Predicted", "Time" : "3/21/2014 11:21:51 AM", "TimeRemaining" : "00:12:24", "Revenue" : "Revenue", "Route" : "0" },
{  "Line" : "Orange", "Trip" : 483, "PlatformKey" : "OFORS", "InformationType" : "Predicted", "Time" : "3/21/2014 11:24:28 AM", "TimeRemaining" : "00:15:01", "Revenue" : "Revenue", "Route" : "0" },
{  "Line" : "Orange", "Trip" : 8905, "PlatformKey" : "OSULS", "InformationType" : "Predicted", "Time" : "3/21/2014 11:13:17 AM", "TimeRemaining" : "00:03:50", "Revenue" : "Revenue", "Route" : "0" },
{  "Line" : "Orange", "Trip" : 8905, "PlatformKey" : "OCOMS", "InformationType" : "Predicted", "Time" : "3/21/2014 11:15:31 AM", "TimeRemaining" : "00:06:04", "Revenue" : "Revenue", "Route" : "0" },
{  "Line" : "Orange", "Trip" : 8905, "PlatformKey" : "ONSTS", "InformationType" : "Predicted", "Time" : "3/21/2014 11:17:56 AM", "TimeRemaining" : "00:08:29", "Revenue" : "Revenue", "Route" : "0" },
{  "Line" : "Orange", "Trip" : 8905, "PlatformKey" : "OHAYS", "InformationType" : "Predicted", "Time" : "3/21/2014 11:19:23 AM", "TimeRemaining" : "00:09:56", "Revenue" : "Revenue", "Route" : "0" },
{  "Line" : "Orange", "Trip" : 8905, "PlatformKey" : "OSTSS", "InformationType" : "Predicted", "Time" : "3/21/2014 11:20:53 AM", "TimeRemaining" : "00:11:26", "Revenue" : "Revenue", "Route" : "0" },
{  "Line" : "Orange", "Trip" : 8905, "PlatformKey" : "ODTSS", "InformationType" : "Predicted", "Time" : "3/21/2014 11:22:20 AM", "TimeRemaining" : "00:12:53", "Revenue" : "Revenue", "Route" : "0" },
{  "Line" : "Orange", "Trip" : 8905, "PlatformKey" : "OCHSS", "InformationType" : "Predicted", "Time" : "3/21/2014 11:23:52 AM", "TimeRemaining" : "00:14:25", "Revenue" : "Revenue", "Route" : "0" },
{  "Line" : "Orange", "Trip" : 8905, "PlatformKey" : "ONEMS", "InformationType" : "Predicted", "Time" : "3/21/2014 11:24:45 AM", "TimeRemaining" : "00:15:18", "Revenue" : "Revenue", "Route" : "0" },
{  "Line" : "Orange", "Trip" : 8905, "PlatformKey" : "OBACS", "InformationType" : "Predicted", "Time" : "3/21/2014 11:26:48 AM", "TimeRemaining" : "00:17:21", "Revenue" : "Revenue", "Route" : "0" },
{  "Line" : "Orange", "Trip" : 8905, "PlatformKey" : "OMASS", "InformationType" : "Predicted", "Time" : "3/21/2014 11:29:21 AM", "TimeRemaining" : "00:19:54", "Revenue" : "Revenue", "Route" : "0" },
{  "Line" : "Orange", "Trip" : 5002, "PlatformKey" : "OGREN", "InformationType" : "Predicted", "Time" : "3/21/2014 11:09:44 AM", "TimeRemaining" : "00:00:17", "Revenue" : "Revenue", "Route" : "0" },
{  "Line" : "Orange", "Trip" : 5002, "PlatformKey" : "OSTON", "InformationType" : "Predicted", "Time" : "3/21/2014 11:11:21 AM", "TimeRemaining" : "00:01:54", "Revenue" : "Revenue", "Route" : "0" },
{  "Line" : "Orange", "Trip" : 5002, "PlatformKey" : "OJACN", "InformationType" : "Predicted", "Time" : "3/21/2014 11:13:10 AM", "TimeRemaining" : "00:03:43", "Revenue" : "Revenue", "Route" : "0" },
{  "Line" : "Orange", "Trip" : 5002, "PlatformKey" : "OROXN", "InformationType" : "Predicted", "Time" : "3/21/2014 11:14:54 AM", "TimeRemaining" : "00:05:27", "Revenue" : "Revenue", "Route" : "0" },
{  "Line" : "Orange", "Trip" : 5002, "PlatformKey" : "ORUGN", "InformationType" : "Predicted", "Time" : "3/21/2014 11:16:24 AM", "TimeRemaining" : "00:06:57", "Revenue" : "Revenue", "Route" : "0" },
{  "Line" : "Orange", "Trip" : 5002, "PlatformKey" : "OMASN", "InformationType" : "Predicted", "Time" : "3/21/2014 11:17:55 AM", "TimeRemaining" : "00:08:28", "Revenue" : "Revenue", "Route" : "0" },
{  "Line" : "Orange", "Trip" : 5002, "PlatformKey" : "OBACN", "InformationType" : "Predicted", "Time" : "3/21/2014 11:20:09 AM", "TimeRemaining" : "00:10:42", "Revenue" : "Revenue", "Route" : "0" },
{  "Line" : "Orange", "Trip" : 5002, "PlatformKey" : "ONEMN", "InformationType" : "Predicted", "Time" : "3/21/2014 11:22:23 AM", "TimeRemaining" : "00:12:56", "Revenue" : "Revenue", "Route" : "0" },
{  "Line" : "Orange", "Trip" : 5002, "PlatformKey" : "OCHNN", "InformationType" : "Predicted", "Time" : "3/21/2014 11:23:49 AM", "TimeRemaining" : "00:14:22", "Revenue" : "Revenue", "Route" : "0" },
{  "Line" : "Orange", "Trip" : 5002, "PlatformKey" : "ODTNN", "InformationType" : "Predicted", "Time" : "3/21/2014 11:25:05 AM", "TimeRemaining" : "00:15:38", "Revenue" : "Revenue", "Route" : "0" },
{  "Line" : "Orange", "Trip" : 5002, "PlatformKey" : "OSTNN", "InformationType" : "Predicted", "Time" : "3/21/2014 11:26:33 AM", "TimeRemaining" : "00:17:06", "Revenue" : "Revenue", "Route" : "0" },
{  "Line" : "Orange", "Trip" : 5002, "PlatformKey" : "OHAYN", "InformationType" : "Predicted", "Time" : "3/21/2014 11:27:51 AM", "TimeRemaining" : "00:18:24", "Revenue" : "Revenue", "Route" : "0" },
{  "Line" : "Orange", "Trip" : 9846, "PlatformKey" : "OMALS", "InformationType" : "Predicted", "Time" : "3/21/2014 11:14:57 AM", "TimeRemaining" : "00:05:30", "Revenue" : "Revenue", "Route" : "0" },
{  "Line" : "Orange", "Trip" : 9846, "PlatformKey" : "OWELS", "InformationType" : "Predicted", "Time" : "3/21/2014 11:18:36 AM", "TimeRemaining" : "00:09:09", "Revenue" : "Revenue", "Route" : "0" },
{  "Line" : "Orange", "Trip" : 9846, "PlatformKey" : "OSULS", "InformationType" : "Predicted", "Time" : "3/21/2014 11:23:37 AM", "TimeRemaining" : "00:14:10", "Revenue" : "Revenue", "Route" : "0" },
{  "Line" : "Orange", "Trip" : 9846, "PlatformKey" : "OCOMS", "InformationType" : "Predicted", "Time" : "3/21/2014 11:25:51 AM", "TimeRemaining" : "00:16:24", "Revenue" : "Revenue", "Route" : "0" },
{  "Line" : "Orange", "Trip" : 9846, "PlatformKey" : "ONSTS", "InformationType" : "Predicted", "Time" : "3/21/2014 11:28:16 AM", "TimeRemaining" : "00:18:49", "Revenue" : "Revenue", "Route" : "0" },
{  "Line" : "Orange", "Trip" : 1174, "PlatformKey" : "ORUGN", "InformationType" : "Predicted", "Time" : "3/21/2014 11:09:52 AM", "TimeRemaining" : "00:00:25", "Revenue" : "Revenue", "Route" : "0" },
{  "Line" : "Orange", "Trip" : 1174, "PlatformKey" : "OMASN", "InformationType" : "Predicted", "Time" : "3/21/2014 11:11:23 AM", "TimeRemaining" : "00:01:56", "Revenue" : "Revenue", "Route" : "0" },
{  "Line" : "Orange", "Trip" : 1174, "PlatformKey" : "OBACN", "InformationType" : "Predicted", "Time" : "3/21/2014 11:13:37 AM", "TimeRemaining" : "00:04:10", "Revenue" : "Revenue", "Route" : "0" },
{  "Line" : "Orange", "Trip" : 1174, "PlatformKey" : "ONEMN", "InformationType" : "Predicted", "Time" : "3/21/2014 11:15:51 AM", "TimeRemaining" : "00:06:24", "Revenue" : "Revenue", "Route" : "0" },
{  "Line" : "Orange", "Trip" : 1174, "PlatformKey" : "OCHNN", "InformationType" : "Predicted", "Time" : "3/21/2014 11:17:17 AM", "TimeRemaining" : "00:07:50", "Revenue" : "Revenue", "Route" : "0" },
{  "Line" : "Orange", "Trip" : 1174, "PlatformKey" : "ODTNN", "InformationType" : "Predicted", "Time" : "3/21/2014 11:18:33 AM", "TimeRemaining" : "00:09:06", "Revenue" : "Revenue", "Route" : "0" },
{  "Line" : "Orange", "Trip" : 1174, "PlatformKey" : "OSTNN", "InformationType" : "Predicted", "Time" : "3/21/2014 11:20:01 AM", "TimeRemaining" : "00:10:34", "Revenue" : "Revenue", "Route" : "0" },
{  "Line" : "Orange", "Trip" : 1174, "PlatformKey" : "OHAYN", "InformationType" : "Predicted", "Time" : "3/21/2014 11:21:19 AM", "TimeRemaining" : "00:11:52", "Revenue" : "Revenue", "Route" : "0" },
{  "Line" : "Orange", "Trip" : 1174, "PlatformKey" : "ONSTN", "InformationType" : "Predicted", "Time" : "3/21/2014 11:24:35 AM", "TimeRemaining" : "00:15:08", "Revenue" : "Revenue", "Route" : "0" },
{  "Line" : "Orange", "Trip" : 1174, "PlatformKey" : "OCOMN", "InformationType" : "Predicted", "Time" : "3/21/2014 11:26:44 AM", "TimeRemaining" : "00:17:17", "Revenue" : "Revenue", "Route" : "0" },
{  "Line" : "Orange", "Trip" : 1174, "PlatformKey" : "OSULN", "InformationType" : "Predicted", "Time" : "3/21/2014 11:28:48 AM", "TimeRemaining" : "00:19:21", "Revenue" : "Revenue", "Route" : "0" },
{  "Line" : "Orange", "Trip" : 5986, "PlatformKey" : "OMALS", "InformationType" : "Predicted", "Time" : "3/21/2014 11:10:19 AM", "TimeRemaining" : "00:00:52", "Revenue" : "Revenue", "Route" : "0" },
{  "Line" : "Orange", "Trip" : 5986, "PlatformKey" : "OWELS", "InformationType" : "Predicted", "Time" : "3/21/2014 11:13:58 AM", "TimeRemaining" : "00:04:31", "Revenue" : "Revenue", "Route" : "0" },
{  "Line" : "Orange", "Trip" : 5986, "PlatformKey" : "OSULS", "InformationType" : "Predicted", "Time" : "3/21/2014 11:18:59 AM", "TimeRemaining" : "00:09:32", "Revenue" : "Revenue", "Route" : "0" },
{  "Line" : "Orange", "Trip" : 5986, "PlatformKey" : "OCOMS", "InformationType" : "Predicted", "Time" : "3/21/2014 11:21:13 AM", "TimeRemaining" : "00:11:46", "Revenue" : "Revenue", "Route" : "0" },
{  "Line" : "Orange", "Trip" : 5986, "PlatformKey" : "ONSTS", "InformationType" : "Predicted", "Time" : "3/21/2014 11:23:38 AM", "TimeRemaining" : "00:14:11", "Revenue" : "Revenue", "Route" : "0" },
{  "Line" : "Orange", "Trip" : 5986, "PlatformKey" : "OHAYS", "InformationType" : "Predicted", "Time" : "3/21/2014 11:25:05 AM", "TimeRemaining" : "00:15:38", "Revenue" : "Revenue", "Route" : "0" },
{  "Line" : "Orange", "Trip" : 5986, "PlatformKey" : "OSTSS", "InformationType" : "Predicted", "Time" : "3/21/2014 11:26:35 AM", "TimeRemaining" : "00:17:08", "Revenue" : "Revenue", "Route" : "0" },
{  "Line" : "Orange", "Trip" : 5986, "PlatformKey" : "ODTSS", "InformationType" : "Predicted", "Time" : "3/21/2014 11:28:02 AM", "TimeRemaining" : "00:18:35", "Revenue" : "Revenue", "Route" : "0" },
{  "Line" : "Orange", "Trip" : 9845, "PlatformKey" : "OOAKN", "InformationType" : "Predicted", "Time" : "3/21/2014 11:09:56 AM", "TimeRemaining" : "00:00:29", "Revenue" : "Revenue", "Route" : "0" },
{  "Line" : "Orange", "Trip" : 4651, "PlatformKey" : "OCOMS", "InformationType" : "Predicted", "Time" : "3/21/2014 11:09:32 AM", "TimeRemaining" : "00:00:05", "Revenue" : "Revenue", "Route" : "0" },
{  "Line" : "Orange", "Trip" : 4651, "PlatformKey" : "ONSTS", "InformationType" : "Predicted", "Time" : "3/21/2014 11:11:57 AM", "TimeRemaining" : "00:02:30", "Revenue" : "Revenue", "Route" : "0" },
{  "Line" : "Orange", "Trip" : 4651, "PlatformKey" : "OHAYS", "InformationType" : "Predicted", "Time" : "3/21/2014 11:13:24 AM", "TimeRemaining" : "00:03:57", "Revenue" : "Revenue", "Route" : "0" },
{  "Line" : "Orange", "Trip" : 4651, "PlatformKey" : "OSTSS", "InformationType" : "Predicted", "Time" : "3/21/2014 11:14:54 AM", "TimeRemaining" : "00:05:27", "Revenue" : "Revenue", "Route" : "0" },
{  "Line" : "Orange", "Trip" : 4651, "PlatformKey" : "ODTSS", "InformationType" : "Predicted", "Time" : "3/21/2014 11:16:21 AM", "TimeRemaining" : "00:06:54", "Revenue" : "Revenue", "Route" : "0" },
{  "Line" : "Orange", "Trip" : 4651, "PlatformKey" : "OCHSS", "InformationType" : "Predicted", "Time" : "3/21/2014 11:17:53 AM", "TimeRemaining" : "00:08:26", "Revenue" : "Revenue", "Route" : "0" },
{  "Line" : "Orange", "Trip" : 4651, "PlatformKey" : "ONEMS", "InformationType" : "Predicted", "Time" : "3/21/2014 11:18:46 AM", "TimeRemaining" : "00:09:19", "Revenue" : "Revenue", "Route" : "0" },
{  "Line" : "Orange", "Trip" : 4651, "PlatformKey" : "OBACS", "InformationType" : "Predicted", "Time" : "3/21/2014 11:20:49 AM", "TimeRemaining" : "00:11:22", "Revenue" : "Revenue", "Route" : "0" },
{  "Line" : "Orange", "Trip" : 4651, "PlatformKey" : "OMASS", "InformationType" : "Predicted", "Time" : "3/21/2014 11:23:22 AM", "TimeRemaining" : "00:13:55", "Revenue" : "Revenue", "Route" : "0" },
{  "Line" : "Orange", "Trip" : 4651, "PlatformKey" : "ORUGS", "InformationType" : "Predicted", "Time" : "3/21/2014 11:24:50 AM", "TimeRemaining" : "00:15:23", "Revenue" : "Revenue", "Route" : "0" },
{  "Line" : "Orange", "Trip" : 4651, "PlatformKey" : "OROXS", "InformationType" : "Predicted", "Time" : "3/21/2014 11:26:33 AM", "TimeRemaining" : "00:17:06", "Revenue" : "Revenue", "Route" : "0" },
{  "Line" : "Orange", "Trip" : 4651, "PlatformKey" : "OJACS", "InformationType" : "Predicted", "Time" : "3/21/2014 11:28:11 AM", "TimeRemaining" : "00:18:44", "Revenue" : "Revenue", "Route" : "0" }
]